zookeeper_utils/__init__.py
zookeeper_utils/cli.py
zookeeper_utils/filter_globs.py
zookeeper_utils/snapshot.py
zookeeper_utils/txlog.py
zookeeper_utils-0.0.3.dist-info/LICENSE
zookeeper_utils-0.0.3.dist-info/METADATA
zookeeper_utils-0.0.3.dist-info/WHEEL
zookeeper_utils-0.0.3.dist-info/entry_points.txt
zookeeper_utils-0.0.3.dist-info/top_level.txt
zookeeper_utils-0.0.3.dist-info/RECORD
