Metadata-Version: 2.1
Name: zookeeper-utils
Version: 0.0.3
Summary: Utilities to inspect ZooKeeper snapshots and transaction logs
Author-email: Filippo Ghibellini <f.ghibellini@gmail.com>
Project-URL: Homepage, https://github.com/fghibellini/zookeeper-utils
Project-URL: Issues, https://github.com/fghibellini/zookeeper-utils/issues
Classifier: Programming Language :: Python :: 3
Classifier: License :: OSI Approved :: MIT License
Classifier: Operating System :: OS Independent
Requires-Python: >=3.8
License-File: LICENSE
